bearlib/__init__.py
bearlib/logging/core.py
bearlib/logging/webhooks.py
bearlib/notifiers/email.py
bearlib/oracle/factories.py
bearlib_py-0.3.7.dist-info/LICENSE
bearlib_py-0.3.7.dist-info/WHEEL
bearlib_py-0.3.7.dist-info/METADATA
bearlib_py-0.3.7.dist-info/RECORD
